alice/client/api.py
alice/client/models/__init__.py
alice/client/models/dto.py
alice/client/models/llm.py
alice_client-0.0.1.dist-info/LICENSE
alice_client-0.0.1.dist-info/METADATA
alice_client-0.0.1.dist-info/WHEEL
alice_client-0.0.1.dist-info/top_level.txt
alice_client-0.0.1.dist-info/RECORD
