Metadata-Version: 2.1
Name: alice-client
Version: 0.0.1
Summary: Client for the Alice AI virtual assistant server.
Home-page: https://github.com/AliceHomeAI/alice-server
Author: Jordan Maxwell
Maintainer: Jordan Maxwell
License: GNU General Public License v2.0
Classifier: Programming Language :: Python :: 3
License-File: LICENSE
